{"v":"5.5.10","fr":60,"ip":330,"op":631,"w":1248,"h":800,"nm":"Offers Tab","ddd":0,"assets":[{"id":"comp_0","layers":[{"ddd":0,"ind":1,"ty":4,"nm":"Upcoming_Card 6 Outlines","sr":1,"ks":{"o":{"a":0,"k":100,"ix":11},"r":{"a":0,"k":0,"ix":10},"p":{"a":0,"k":[720,2204,0],"ix":2},"a":{"a":0,"k":[109,45,0],"ix":1},"s":{"a":0,"k":[400,400,100],"ix":6}},"ao":0,"shapes":[{"ty":"gr","it":[{"ind":0,"ty":"sh","ix":1,"ks":{"a":0,"k":{"i":[[-0.139,-0.178],[0.174,-0.143],[-0.65,-1.452],[0.465,-0.619],[0.128,0],[0.081,0.071],[-0.139,0.178],[0.65,1.487],[-0.255,0.535],[-0.046,0.023]],"o":[[0.139,0.178],[-0.046,0.036],[0.836,1.88],[-0.069,0.095],[-0.093,0],[-0.174,-0.143],[0.36,-0.464],[-0.464,-1.059],[0.267,-0.571],[0.174,-0.143]],"v":[[0.586,-5.861],[0.528,-5.278],[0.11,-2.874],[-0.192,0.921],[-0.505,1.076],[-0.76,0.982],[-0.83,0.398],[-0.633,-2.54],[-0.656,-5.004],[0.017,-5.92]],"c":true},"ix":2},"nm":"Path 1","mn":"ADBE Vector Shape - Group","hd":false},{"ind":1,"ty":"sh","ix":2,"ks":{"a":0,"k":{"i":[[-0.139,-0.179],[0.174,-0.143],[-0.986,-2.237],[0.661,-0.844],[0.116,0],[0.081,0.071],[-0.139,0.178],[0.987,2.226],[-0.023,0.024]],"o":[[0.139,0.178],[-0.07,0.059],[1.161,2.63],[-0.058,0.107],[-0.093,0],[-0.175,-0.143],[0.534,-0.702],[-1.253,-2.831],[0.174,-0.142]],"v":[[4.996,-8.657],[4.938,-8.074],[4.276,-4.385],[3.859,0.91],[3.557,1.076],[3.302,0.982],[3.232,0.398],[3.545,-4.04],[4.427,-8.717]],"c":true},"ix":2},"nm":"Path 2","mn":"ADBE Vector Shape - Group","hd":false},{"ind":2,"ty":"sh","ix":3,"ks":{"a":0,"k":{"i":[[-0.14,-0.179],[0.174,-0.143],[-0.986,-2.237],[0.662,-0.844],[0.127,0],[0.081,0.071],[-0.14,0.178],[0.986,2.226],[-0.023,0.024]],"o":[[0.139,0.178],[-0.07,0.059],[1.161,2.63],[-0.058,0.107],[-0.093,0],[-0.174,-0.143],[0.533,-0.702],[-1.253,-2.831],[0.174,-0.142]],"v":[[-3.336,-8.657],[-3.394,-8.074],[-4.056,-4.385],[-4.474,0.91],[-4.775,1.076],[-5.031,0.982],[-5.1,0.398],[-4.787,-4.04],[-3.905,-8.717]],"c":true},"ix":2},"nm":"Path 3","mn":"ADBE Vector Shape - Group","hd":false},{"ind":3,"ty":"sh","ix":4,"ks":{"a":0,"k":{"i":[[0,0],[-0.035,-0.192],[0,0],[0.232,0],[0,0],[0.035,0.192],[0,0],[-0.221,0]],"o":[[0.196,0],[0,0],[0,0.226],[0,0],[-0.196,0],[0,0],[0,-0.226],[0,0]],"v":[[8.361,2.54],[8.761,2.882],[8.767,2.956],[8.361,3.372],[-8.361,3.372],[-8.761,3.031],[-8.767,2.956],[-8.361,2.54]],"c":true},"ix":2},"nm":"Path 4","mn":"ADBE Vector Shape - Group","hd":false},{"ind":4,"ty":"sh","ix":5,"ks":{"a":0,"k":{"i":[[0,0],[0,0],[0.917,0],[0,0],[0.209,0.714],[0,0]],"o":[[0,0],[-0.232,0.595],[0,0],[-1.103,0],[0,0],[0,0]],"v":[[7.677,3.979],[6.133,7.859],[4.172,8.859],[-4.276,8.859],[-6.539,7.632],[-7.642,3.979]],"c":true},"ix":2},"nm":"Path 5","mn":"ADBE Vector Shape - Group","hd":false},{"ty":"mm","mm":1,"nm":"Merge Paths 1","mn":"ADBE Vector Filter - Merge","hd":false},{"ty":"fl","c":{"a":0,"k":[0.980000035903,0.980000035903,0.980000035903,1],"ix":4},"o":{"a":0,"k":100,"ix":5},"r":1,"bm":0,"nm":"Fill 1","mn":"ADBE Vector Graphic - Fill","hd":false},{"ty":"tr","p":{"a":0,"k":[28.11,28.203],"ix":2},"a":{"a":0,"k":[0,0],"ix":1},"s":{"a":0,"k":[100,100],"ix":3},"r":{"a":0,"k":0,"ix":6},"o":{"a":0,"k":100,"ix":7},"sk":{"a":0,"k":0,"ix":4},"sa":{"a":0,"k":0,"ix":5},"nm":"Transform"}],"nm":"Group 1","np":9,"cix":2,"bm":0,"ix":1,"mn":"ADBE Vector Group","hd":false},{"ty":"gr","it":[{"ind":0,"ty":"sh","ix":1,"ks":{"a":0,"k":{"i":[[-8.716,0],[0,-8.717],[8.716,0],[0,8.716]],"o":[[8.716,0],[0,8.716],[-8.716,0],[0,-8.717]],"v":[[0,-15.783],[15.783,0.001],[0,15.783],[-15.783,0.001]],"c":true},"ix":2},"nm":"Path 1","mn":"ADBE Vector Shape - Group","hd":false},{"ty":"fl","c":{"a":0,"k":[0,0.584313750267,1,1],"ix":4},"o":{"a":0,"k":100,"ix":5},"r":1,"bm":0,"nm":"Fill 1","mn":"ADBE Vector Graphic - Fill","hd":false},{"ty":"tr","p":{"a":0,"k":[28,28.013],"ix":2},"a":{"a":0,"k":[0,0],"ix":1},"s":{"a":0,"k":[100,100],"ix":3},"r":{"a":0,"k":0,"ix":6},"o":{"a":0,"k":100,"ix":7},"sk":{"a":0,"k":0,"ix":4},"sa":{"a":0,"k":0,"ix":5},"nm":"Transform"}],"nm":"Group 4","np":4,"cix":2,"bm":0,"ix":4,"mn":"ADBE Vector Group","hd":false},{"ty":"gr","it":[{"ind":0,"ty":"sh","ix":1,"ks":{"a":0,"k":{"i":[[0,0],[0,0],[0,0],[0,0]],"o":[[0,0],[0,0],[0,0],[0,0]],"v":[[-74.898,-5],[74.898,-5],[74.898,5],[-74.898,5]],"c":true},"ix":2},"nm":"Path 1","mn":"ADBE Vector Shape - Group","hd":false},{"ty":"fl","c":{"a":0,"k":[0.690196096897,0.690196096897,0.690196096897,1],"ix":4},"o":{"a":0,"k":60,"ix":5},"r":1,"bm":0,"nm":"Fill 1","mn":"ADBE Vector Graphic - Fill","hd":false},{"ty":"tr","p":{"a":0,"k":[131.102,27.798],"ix":2},"a":{"a":0,"k":[0,0],"ix":1},"s":{"a":0,"k":[100,100],"ix":3},"r":{"a":0,"k":0,"ix":6},"o":{"a":0,"k":100,"ix":7},"sk":{"a":0,"k":0,"ix":4},"sa":{"a":0,"k":0,"ix":5},"nm":"Transform"}],"nm":"Group 5","np":4,"cix":2,"bm":0,"ix":5,"mn":"ADBE Vector Group","hd":false},{"ty":"gr","it":[{"ind":0,"ty":"sh","ix":1,"ks":{"a":0,"k":{"i":[[0,0],[0,0],[0,0],[0,0]],"o":[[0,0],[0,0],[0,0],[0,0]],"v":[[-97,-5],[97,-5],[97,5],[-97,5]],"c":true},"ix":2},"nm":"Path 1","mn":"ADBE Vector Shape - Group","hd":false},{"ty":"fl","c":{"a":0,"k":[0.690196096897,0.690196096897,0.690196096897,1],"ix":4},"o":{"a":0,"k":60,"ix":5},"r":1,"bm":0,"nm":"Fill 1","mn":"ADBE Vector Graphic - Fill","hd":false},{"ty":"tr","p":{"a":0,"k":[109,73],"ix":2},"a":{"a":0,"k":[0,0],"ix":1},"s":{"a":0,"k":[100,100],"ix":3},"r":{"a":0,"k":0,"ix":6},"o":{"a":0,"k":100,"ix":7},"sk":{"a":0,"k":0,"ix":4},"sa":{"a":0,"k":0,"ix":5},"nm":"Transform"}],"nm":"Group 6","np":4,"cix":2,"bm":0,"ix":6,"mn":"ADBE Vector Group","hd":false},{"ty":"gr","it":[{"ind":0,"ty":"sh","ix":1,"ks":{"a":0,"k":{"i":[[0,0],[0,0],[0,0],[0,0]],"o":[[0,0],[0,0],[0,0],[0,0]],"v":[[-97,-5],[97,-5],[97,5],[-97,5]],"c":true},"ix":2},"nm":"Path 1","mn":"ADBE Vector Shape - Group","hd":false},{"ty":"fl","c":{"a":0,"k":[0.690196096897,0.690196096897,0.690196096897,1],"ix":4},"o":{"a":0,"k":60,"ix":5},"r":1,"bm":0,"nm":"Fill 2","mn":"ADBE Vector Graphic - Fill","hd":false},{"ty":"tr","p":{"a":0,"k":[109,56],"ix":2},"a":{"a":0,"k":[0,0],"ix":1},"s":{"a":0,"k":[100,100],"ix":3},"r":{"a":0,"k":0,"ix":6},"o":{"a":0,"k":100,"ix":7},"sk":{"a":0,"k":0,"ix":4},"sa":{"a":0,"k":0,"ix":5},"nm":"Transform"}],"nm":"Group 7","np":4,"cix":2,"bm":0,"ix":7,"mn":"ADBE Vector Group","hd":false}],"ip":0,"op":1800,"st":0,"bm":0},{"ddd":0,"ind":2,"ty":4,"nm":"Upcoming_Card 5 Outlines","sr":1,"ks":{"o":{"a":0,"k":100,"ix":11},"r":{"a":0,"k":0,"ix":10},"p":{"a":0,"k":[720,1804,0],"ix":2},"a":{"a":0,"k":[109,45,0],"ix":1},"s":{"a":0,"k":[400,400,100],"ix":6}},"ao":0,"shapes":[{"ty":"gr","it":[{"ind":0,"ty":"sh","ix":1,"ks":{"a":0,"k":{"i":[[-0.063,-0.321],[0,0],[0,0],[-0.273,0],[0,0],[-0.23,-0.114],[0.408,-0.824],[0,0],[0.633,0],[0,0],[0.151,0.783],[0,0],[0,0.106],[0,0],[0,0],[0,0],[0.08,0.319],[0.001,0],[-0.321,0.081],[0,0],[0,0],[-0.042,0.009]],"o":[[0,0],[0,0],[0.227,-0.116],[0,0],[0.256,0],[0.824,0.408],[0,0],[-0.281,0.567],[0,0],[-0.798,0],[0,0],[-0.02,-0.104],[0,0],[0,0],[0,0],[-0.319,0.08],[0,-0.001],[-0.079,-0.322],[0,0],[0,0],[0.038,-0.017],[0.321,-0.063]],"v":[[-5.605,-7.823],[-5.605,-7.821],[-4.91,-4.213],[-4.152,-4.394],[7.766,-4.394],[8.505,-4.221],[9.258,-1.99],[6.557,3.465],[5.064,4.391],[-3.102,4.391],[-4.736,3.041],[-5.788,-2.414],[-5.818,-2.729],[-5.816,-2.638],[-6.648,-6.963],[-8.863,-6.405],[-9.587,-6.838],[-9.588,-6.84],[-9.15,-7.568],[-6.471,-8.242],[-6.421,-8.252],[-6.299,-8.29]],"c":true},"ix":2},"nm":"Path 1","mn":"ADBE Vector Shape - Group","hd":false},{"ind":1,"ty":"sh","ix":2,"ks":{"a":0,"k":{"i":[[-0.656,0],[0,-0.661],[0.656,0],[0,0.662]],"o":[[0.656,0],[0,0.662],[-0.656,0],[0,-0.661]],"v":[[3.96,5.957],[5.148,7.155],[3.96,8.353],[2.773,7.155]],"c":true},"ix":2},"nm":"Path 2","mn":"ADBE Vector Shape - Group","hd":false},{"ind":2,"ty":"sh","ix":3,"ks":{"a":0,"k":{"i":[[-0.656,0],[0,-0.661],[0.655,0],[0,0.662]],"o":[[0.655,0],[0,0.662],[-0.656,0],[0,-0.661]],"v":[[-2.37,5.957],[-1.184,7.155],[-2.37,8.353],[-3.557,7.155]],"c":true},"ix":2},"nm":"Path 3","mn":"ADBE Vector Shape - Group","hd":false},{"ty":"mm","mm":1,"nm":"Merge Paths 1","mn":"ADBE Vector Filter - Merge","hd":false},{"ty":"fl","c":{"a":0,"k":[1,1,1,1],"ix":4},"o":{"a":0,"k":100,"ix":5},"r":1,"bm":0,"nm":"Fill 1","mn":"ADBE Vector Graphic - Fill","hd":false},{"ty":"tr","p":{"a":0,"k":[28.219,28.37],"ix":2},"a":{"a":0,"k":[0,0],"ix":1},"s":{"a":0,"k":[100,100],"ix":3},"r":{"a":0,"k":0,"ix":6},"o":{"a":0,"k":100,"ix":7},"sk":{"a":0,"k":0,"ix":4},"sa":{"a":0,"k":0,"ix":5},"nm":"Transform"}],"nm":"Group 1","np":7,"cix":2,"bm":0,"ix":1,"mn":"ADBE Vector Group","hd":false},{"ty":"gr","it":[{"ind":0,"ty":"sh","ix":1,"ks":{"a":0,"k":{"i":[[-8.76,0],[0,-8.76],[8.76,0],[0,8.76]],"o":[[8.76,0],[0,8.76],[-8.76,0],[0,-8.76]],"v":[[0,-15.861],[15.861,0],[0,15.861],[-15.861,0]],"c":true},"ix":2},"nm":"Path 1","mn":"ADBE Vector Shape - Group","hd":false},{"ty":"fl","c":{"a":0,"k":[0,0.583999992819,1,1],"ix":4},"o":{"a":0,"k":100,"ix":5},"r":1,"bm":0,"nm":"Fill 1","mn":"ADBE Vector Graphic - Fill","hd":false},{"ty":"tr","p":{"a":0,"k":[28,28],"ix":2},"a":{"a":0,"k":[0,0],"ix":1},"s":{"a":0,"k":[100,100],"ix":3},"r":{"a":0,"k":0,"ix":6},"o":{"a":0,"k":100,"ix":7},"sk":{"a":0,"k":0,"ix":4},"sa":{"a":0,"k":0,"ix":5},"nm":"Transform"}],"nm":"Group 4","np":4,"cix":2,"bm":0,"ix":4,"mn":"ADBE Vector Group","hd":false},{"ty":"gr","it":[{"ind":0,"ty":"sh","ix":1,"ks":{"a":0,"k":{"i":[[0,0],[0,0],[0,0],[0,0]],"o":[[0,0],[0,0],[0,0],[0,0]],"v":[[-74.898,-5],[74.898,-5],[74.898,5],[-74.898,5]],"c":true},"ix":2},"nm":"Path 1","mn":"ADBE Vector Shape - Group","hd":false},{"ty":"fl","c":{"a":0,"k":[0.690196096897,0.690196096897,0.690196096897,1],"ix":4},"o":{"a":0,"k":60,"ix":5},"r":1,"bm":0,"nm":"Fill 2","mn":"ADBE Vector Graphic - Fill","hd":false},{"ty":"tr","p":{"a":0,"k":[131.102,27.798],"ix":2},"a":{"a":0,"k":[0,0],"ix":1},"s":{"a":0,"k":[100,100],"ix":3},"r":{"a":0,"k":0,"ix":6},"o":{"a":0,"k":100,"ix":7},"sk":{"a":0,"k":0,"ix":4},"sa":{"a":0,"k":0,"ix":5},"nm":"Transform"}],"nm":"Group 5","np":4,"cix":2,"bm":0,"ix":5,"mn":"ADBE Vector Group","hd":false},{"ty":"gr","it":[{"ind":0,"ty":"sh","ix":1,"ks":{"a":0,"k":{"i":[[0,0],[0,0],[0,0],[0,0]],"o":[[0,0],[0,0],[0,0],[0,0]],"v":[[-97,-5],[97,-5],[97,5],[-97,5]],"c":true},"ix":2},"nm":"Path 1","mn":"ADBE Vector Shape - Group","hd":false},{"ty":"fl","c":{"a":0,"k":[0.690196096897,0.690196096897,0.690196096897,1],"ix":4},"o":{"a":0,"k":60,"ix":5},"r":1,"bm":0,"nm":"Fill 2","mn":"ADBE Vector Graphic - Fill","hd":false},{"ty":"tr","p":{"a":0,"k":[109,73],"ix":2},"a":{"a":0,"k":[0,0],"ix":1},"s":{"a":0,"k":[100,100],"ix":3},"r":{"a":0,"k":0,"ix":6},"o":{"a":0,"k":100,"ix":7},"sk":{"a":0,"k":0,"ix":4},"sa":{"a":0,"k":0,"ix":5},"nm":"Transform"}],"nm":"Group 6","np":4,"cix":2,"bm":0,"ix":6,"mn":"ADBE Vector Group","hd":false},{"ty":"gr","it":[{"ind":0,"ty":"sh","ix":1,"ks":{"a":0,"k":{"i":[[0,0],[0,0],[0,0],[0,0]],"o":[[0,0],[0,0],[0,0],[0,0]],"v":[[-97,-5],[97,-5],[97,5],[-97,5]],"c":true},"ix":2},"nm":"Path 1","mn":"ADBE Vector Shape - Group","hd":false},{"ty":"fl","c":{"a":0,"k":[0.690196096897,0.690196096897,0.690196096897,1],"ix":4},"o":{"a":0,"k":60,"ix":5},"r":1,"bm":0,"nm":"Fill 2","mn":"ADBE Vector Graphic - Fill","hd":false},{"ty":"tr","p":{"a":0,"k":[109,56],"ix":2},"a":{"a":0,"k":[0,0],"ix":1},"s":{"a":0,"k":[100,100],"ix":3},"r":{"a":0,"k":0,"ix":6},"o":{"a":0,"k":100,"ix":7},"sk":{"a":0,"k":0,"ix":4},"sa":{"a":0,"k":0,"ix":5},"nm":"Transform"}],"nm":"Group 7","np":4,"cix":2,"bm":0,"ix":7,"mn":"ADBE Vector Group","hd":false}],"ip":0,"op":1800,"st":0,"bm":0},{"ddd":0,"ind":3,"ty":4,"nm":"Upcoming_Card 4 Outlines","sr":1,"ks":{"o":{"a":0,"k":100,"ix":11},"r":{"a":0,"k":0,"ix":10},"p":{"a":0,"k":[720,1404,0],"ix":2},"a":{"a":0,"k":[109,45,0],"ix":1},"s":{"a":0,"k":[400,400,100],"ix":6}},"ao":0,"shapes":[{"ty":"gr","it":[{"ind":0,"ty":"sh","ix":1,"ks":{"a":0,"k":{"i":[[1.648,0],[1.671,-0.093],[0.086,-0.255],[0,0],[0,0],[0,-0.017],[-0.122,-0.025],[0,0],[0,0],[-0.017,0.003],[-0.001,0.125],[0,0],[0,0],[0.304,0.018]],"o":[[-1.659,0],[-0.276,0.015],[0,0],[0,0],[-0.003,0.016],[0,0.129],[0,0],[0,0],[0.018,0],[0.127,-0.025],[0,0],[0,0],[-0.059,-0.299],[-1.551,-0.092]],"v":[[0.165,-5.993],[-4.831,-5.854],[-5.426,-5.4],[-5.451,-5.313],[-6.128,-1.792],[-6.133,-1.742],[-5.919,-1.48],[-5.865,-1.473],[6.008,-1.473],[6.061,-1.479],[6.277,-1.74],[6.271,-1.792],[5.577,-5.318],[4.962,-5.855]],"c":true},"ix":2},"nm":"Path 1","mn":"ADBE Vector Shape - Group","hd":false},{"ind":1,"ty":"sh","ix":2,"ks":{"a":0,"k":{"i":[[0.742,0],[0,-0.759],[-0.743,0],[0,0.76]],"o":[[-0.743,0],[0,0.76],[0.742,0],[0,-0.759]],"v":[[5.667,0.197],[4.322,1.572],[5.667,2.947],[7.012,1.572]],"c":true},"ix":2},"nm":"Path 2","mn":"ADBE Vector Shape - Group","hd":false},{"ind":2,"ty":"sh","ix":3,"ks":{"a":0,"k":{"i":[[0.742,0],[0,-0.759],[-0.743,0],[0,0.76]],"o":[[-0.743,0],[0,0.76],[0.742,0],[0,-0.759]],"v":[[-5.667,0.197],[-7.012,1.572],[-5.667,2.947],[-4.322,1.572]],"c":true},"ix":2},"nm":"Path 3","mn":"ADBE Vector Shape - Group","hd":false},{"ind":3,"ty":"sh","ix":4,"ks":{"a":0,"k":{"i":[[-0.436,0],[-0.302,-0.015],[-0.105,-0.224],[0,0],[0,-0.038],[-1.202,-0.087],[-0.073,-0.277],[0,0],[0.006,-0.035],[0,-0.566],[0,0],[0.147,0],[0,0],[0,0],[0.369,0],[0,0],[0,0.369],[0,0],[0,0],[0,0],[0.369,0],[0,0],[0,0.369],[0,0],[0,0],[0,0.148],[0,0],[-0.47,0.245],[0,0.014],[-0.007,0.023],[0,0],[-0.282,0.021],[-1.174,0.031],[0,0],[-0.014,0.032],[0,0],[-0.257,0.012]],"o":[[0.416,0],[0.247,0.013],[0,0],[0.017,0.036],[1.177,0.031],[0.286,0.02],[0,0],[0.009,0.037],[0.469,0.245],[0,0],[0,0.148],[0,0],[0,0],[0,0.369],[0,0],[-0.369,0],[0,0],[0,0],[0,0],[0,0.369],[0,0],[-0.37,0],[0,0],[0,0],[-0.148,0],[0,0],[0,-0.567],[-0.003,-0.013],[0,-0.024],[0,0],[0.075,-0.272],[1.18,-0.087],[0,0.002],[0,-0.035],[0,0],[0.099,-0.238],[0.35,-0.018]],"v":[[0.057,-7.958],[1.132,-7.936],[1.704,-7.549],[1.977,-6.962],[2.001,-6.85],[5.572,-6.673],[6.171,-6.174],[7.563,-0.827],[7.568,-0.717],[8.357,0.587],[8.357,5.234],[8.089,5.501],[7.012,5.501],[7.012,7.29],[6.344,7.958],[5.663,7.958],[4.995,7.29],[4.995,5.501],[-4.995,5.501],[-4.995,7.29],[-5.663,7.958],[-6.342,7.958],[-7.012,7.29],[-7.012,5.501],[-8.089,5.501],[-8.357,5.234],[-8.357,0.587],[-7.566,-0.717],[-7.57,-0.758],[-7.56,-0.829],[-6.094,-6.184],[-5.499,-6.673],[-1.967,-6.852],[-1.967,-6.85],[-1.947,-6.954],[-1.708,-7.523],[-1.124,-7.932]],"c":true},"ix":2},"nm":"Path 4","mn":"ADBE Vector Shape - Group","hd":false},{"ty":"mm","mm":1,"nm":"Merge Paths 1","mn":"ADBE Vector Filter - Merge","hd":false},{"ty":"fl","c":{"a":0,"k":[0.980000035903,0.980000035903,0.980000035903,1],"ix":4},"o":{"a":0,"k":100,"ix":5},"r":1,"bm":0,"nm":"Fill 1","mn":"ADBE Vector Graphic - Fill","hd":false},{"ty":"tr","p":{"a":0,"k":[28.398,28],"ix":2},"a":{"a":0,"k":[0,0],"ix":1},"s":{"a":0,"k":[100,100],"ix":3},"r":{"a":0,"k":0,"ix":6},"o":{"a":0,"k":100,"ix":7},"sk":{"a":0,"k":0,"ix":4},"sa":{"a":0,"k":0,"ix":5},"nm":"Transform"}],"nm":"Group 1","np":8,"cix":2,"bm":0,"ix":1,"mn":"ADBE Vector Group","hd":false},{"ty":"gr","it":[{"ind":0,"ty":"sh","ix":1,"ks":{"a":0,"k":{"i":[[-8.791,0],[0,-8.791],[8.791,0],[0,8.79]],"o":[[8.791,0],[0,8.79],[-8.791,0],[0,-8.791]],"v":[[0,-15.917],[15.917,0.001],[0,15.917],[-15.917,0.001]],"c":true},"ix":2},"nm":"Path 1","mn":"ADBE Vector Shape - Group","hd":false},{"ty":"fl","c":{"a":0,"k":[0,0.583999992819,1,1],"ix":4},"o":{"a":0,"k":100,"ix":5},"r":1,"bm":0,"nm":"Fill 1","mn":"ADBE Vector Graphic - Fill","hd":false},{"ty":"tr","p":{"a":0,"k":[28,28],"ix":2},"a":{"a":0,"k":[0,0],"ix":1},"s":{"a":0,"k":[100,100],"ix":3},"r":{"a":0,"k":0,"ix":6},"o":{"a":0,"k":100,"ix":7},"sk":{"a":0,"k":0,"ix":4},"sa":{"a":0,"k":0,"ix":5},"nm":"Transform"}],"nm":"Group 4","np":4,"cix":2,"bm":0,"ix":4,"mn":"ADBE Vector Group","hd":false},{"ty":"gr","it":[{"ind":0,"ty":"sh","ix":1,"ks":{"a":0,"k":{"i":[[0,0],[0,0],[0,0],[0,0]],"o":[[0,0],[0,0],[0,0],[0,0]],"v":[[-74.898,-5],[74.898,-5],[74.898,5],[-74.898,5]],"c":true},"ix":2},"nm":"Path 1","mn":"ADBE Vector Shape - Group","hd":false},{"ty":"fl","c":{"a":0,"k":[0.690196096897,0.690196096897,0.690196096897,1],"ix":4},"o":{"a":0,"k":60,"ix":5},"r":1,"bm":0,"nm":"Fill 2","mn":"ADBE Vector Graphic - Fill","hd":false},{"ty":"tr","p":{"a":0,"k":[131.102,27.798],"ix":2},"a":{"a":0,"k":[0,0],"ix":1},"s":{"a":0,"k":[100,100],"ix":3},"r":{"a":0,"k":0,"ix":6},"o":{"a":0,"k":100,"ix":7},"sk":{"a":0,"k":0,"ix":4},"sa":{"a":0,"k":0,"ix":5},"nm":"Transform"}],"nm":"Group 5","np":4,"cix":2,"bm":0,"ix":5,"mn":"ADBE Vector Group","hd":false},{"ty":"gr","it":[{"ind":0,"ty":"sh","ix":1,"ks":{"a":0,"k":{"i":[[0,0],[0,0],[0,0],[0,0]],"o":[[0,0],[0,0],[0,0],[0,0]],"v":[[-97,-5],[97,-5],[97,5],[-97,5]],"c":true},"ix":2},"nm":"Path 1","mn":"ADBE Vector Shape - Group","hd":false},{"ty":"fl","c":{"a":0,"k":[0.690196096897,0.690196096897,0.690196096897,1],"ix":4},"o":{"a":0,"k":60,"ix":5},"r":1,"bm":0,"nm":"Fill 2","mn":"ADBE Vector Graphic - Fill","hd":false},{"ty":"tr","p":{"a":0,"k":[109,73],"ix":2},"a":{"a":0,"k":[0,0],"ix":1},"s":{"a":0,"k":[100,100],"ix":3},"r":{"a":0,"k":0,"ix":6},"o":{"a":0,"k":100,"ix":7},"sk":{"a":0,"k":0,"ix":4},"sa":{"a":0,"k":0,"ix":5},"nm":"Transform"}],"nm":"Group 6","np":4,"cix":2,"bm":0,"ix":6,"mn":"ADBE Vector Group","hd":false},{"ty":"gr","it":[{"ind":0,"ty":"sh","ix":1,"ks":{"a":0,"k":{"i":[[0,0],[0,0],[0,0],[0,0]],"o":[[0,0],[0,0],[0,0],[0,0]],"v":[[-97,-5],[97,-5],[97,5],[-97,5]],"c":true},"ix":2},"nm":"Path 1","mn":"ADBE Vector Shape - Group","hd":false},{"ty":"fl","c":{"a":0,"k":[0.690196096897,0.690196096897,0.690196096897,1],"ix":4},"o":{"a":0,"k":60,"ix":5},"r":1,"bm":0,"nm":"Fill 2","mn":"ADBE Vector Graphic - Fill","hd":false},{"ty":"tr","p":{"a":0,"k":[109,56],"ix":2},"a":{"a":0,"k":[0,0],"ix":1},"s":{"a":0,"k":[100,100],"ix":3},"r":{"a":0,"k":0,"ix":6},"o":{"a":0,"k":100,"ix":7},"sk":{"a":0,"k":0,"ix":4},"sa":{"a":0,"k":0,"ix":5},"nm":"Transform"}],"nm":"Group 7","np":4,"cix":2,"bm":0,"ix":7,"mn":"ADBE Vector Group","hd":false}],"ip":0,"op":1800,"st":0,"bm":0},{"ddd":0,"ind":4,"ty":4,"nm":"Upcoming_Card 3 Outlines","sr":1,"ks":{"o":{"a":0,"k":100,"ix":11},"r":{"a":0,"k":0,"ix":10},"p":{"a":0,"k":[720,1004,0],"ix":2},"a":{"a":0,"k":[109,45,0],"ix":1},"s":{"a":0,"k":[400,400,100],"ix":6}},"ao":0,"shapes":[{"ty":"gr","it":[{"ind":0,"ty":"sh","ix":1,"ks":{"a":0,"k":{"i":[[-0.139,-0.178],[0.174,-0.143],[-0.65,-1.452],[0.465,-0.619],[0.128,0],[0.081,0.071],[-0.139,0.178],[0.65,1.487],[-0.255,0.535],[-0.046,0.023]],"o":[[0.139,0.178],[-0.046,0.036],[0.836,1.88],[-0.069,0.095],[-0.093,0],[-0.174,-0.143],[0.36,-0.464],[-0.464,-1.059],[0.267,-0.571],[0.174,-0.143]],"v":[[0.586,-5.861],[0.528,-5.278],[0.11,-2.874],[-0.192,0.921],[-0.505,1.076],[-0.76,0.982],[-0.83,0.398],[-0.633,-2.54],[-0.656,-5.004],[0.017,-5.92]],"c":true},"ix":2},"nm":"Path 1","mn":"ADBE Vector Shape - Group","hd":false},{"ind":1,"ty":"sh","ix":2,"ks":{"a":0,"k":{"i":[[-0.139,-0.179],[0.174,-0.143],[-0.986,-2.237],[0.661,-0.844],[0.116,0],[0.081,0.071],[-0.139,0.178],[0.987,2.226],[-0.023,0.024]],"o":[[0.139,0.178],[-0.07,0.059],[1.161,2.63],[-0.058,0.107],[-0.093,0],[-0.175,-0.143],[0.534,-0.702],[-1.253,-2.831],[0.174,-0.142]],"v":[[4.996,-8.657],[4.938,-8.074],[4.276,-4.385],[3.859,0.91],[3.557,1.076],[3.302,0.982],[3.232,0.398],[3.545,-4.04],[4.427,-8.717]],"c":true},"ix":2},"nm":"Path 2","mn":"ADBE Vector Shape - Group","hd":false},{"ind":2,"ty":"sh","ix":3,"ks":{"a":0,"k":{"i":[[-0.14,-0.179],[0.174,-0.143],[-0.986,-2.237],[0.662,-0.844],[0.127,0],[0.081,0.071],[-0.14,0.178],[0.986,2.226],[-0.023,0.024]],"o":[[0.139,0.178],[-0.07,0.059],[1.161,2.63],[-0.058,0.107],[-0.093,0],[-0.174,-0.143],[0.533,-0.702],[-1.253,-2.831],[0.174,-0.142]],"v":[[-3.336,-8.657],[-3.394,-8.074],[-4.056,-4.385],[-4.474,0.91],[-4.775,1.076],[-5.031,0.982],[-5.1,0.398],[-4.787,-4.04],[-3.905,-8.717]],"c":true},"ix":2},"nm":"Path 3","mn":"ADBE Vector Shape - Group","hd":false},{"ind":3,"ty":"sh","ix":4,"ks":{"a":0,"k":{"i":[[0,0],[-0.035,-0.192],[0,0],[0.232,0],[0,0],[0.035,0.192],[0,0],[-0.221,0]],"o":[[0.196,0],[0,0],[0,0.226],[0,0],[-0.196,0],[0,0],[0,-0.226],[0,0]],"v":[[8.361,2.54],[8.761,2.882],[8.767,2.956],[8.361,3.372],[-8.361,3.372],[-8.761,3.031],[-8.767,2.956],[-8.361,2.54]],"c":true},"ix":2},"nm":"Path 4","mn":"ADBE Vector Shape - Group","hd":false},{"ind":4,"ty":"sh","ix":5,"ks":{"a":0,"k":{"i":[[0,0],[0,0],[0.917,0],[0,0],[0.209,0.714],[0,0]],"o":[[0,0],[-0.232,0.595],[0,0],[-1.103,0],[0,0],[0,0]],"v":[[7.677,3.979],[6.133,7.859],[4.172,8.859],[-4.276,8.859],[-6.539,7.632],[-7.642,3.979]],"c":true},"ix":2},"nm":"Path 5","mn":"ADBE Vector Shape - Group","hd":false},{"ty":"mm","mm":1,"nm":"Merge Paths 1","mn":"ADBE Vector Filter - Merge","hd":false},{"ty":"fl","c":{"a":0,"k":[0.980000035903,0.980000035903,0.980000035903,1],"ix":4},"o":{"a":0,"k":100,"ix":5},"r":1,"bm":0,"nm":"Fill 1","mn":"ADBE Vector Graphic - Fill","hd":false},{"ty":"tr","p":{"a":0,"k":[28.11,28.203],"ix":2},"a":{"a":0,"k":[0,0],"ix":1},"s":{"a":0,"k":[100,100],"ix":3},"r":{"a":0,"k":0,"ix":6},"o":{"a":0,"k":100,"ix":7},"sk":{"a":0,"k":0,"ix":4},"sa":{"a":0,"k":0,"ix":5},"nm":"Transform"}],"nm":"Group 1","np":9,"cix":2,"bm":0,"ix":1,"mn":"ADBE Vector Group","hd":false},{"ty":"gr","it":[{"ind":0,"ty":"sh","ix":1,"ks":{"a":0,"k":{"i":[[-8.716,0],[0,-8.717],[8.716,0],[0,8.716]],"o":[[8.716,0],[0,8.716],[-8.716,0],[0,-8.717]],"v":[[0,-15.783],[15.783,0.001],[0,15.783],[-15.783,0.001]],"c":true},"ix":2},"nm":"Path 1","mn":"ADBE Vector Shape - Group","hd":false},{"ty":"fl","c":{"a":0,"k":[0,0.583999992819,1,1],"ix":4},"o":{"a":0,"k":100,"ix":5},"r":1,"bm":0,"nm":"Fill 1","mn":"ADBE Vector Graphic - Fill","hd":false},{"ty":"tr","p":{"a":0,"k":[28,28.013],"ix":2},"a":{"a":0,"k":[0,0],"ix":1},"s":{"a":0,"k":[100,100],"ix":3},"r":{"a":0,"k":0,"ix":6},"o":{"a":0,"k":100,"ix":7},"sk":{"a":0,"k":0,"ix":4},"sa":{"a":0,"k":0,"ix":5},"nm":"Transform"}],"nm":"Group 4","np":4,"cix":2,"bm":0,"ix":4,"mn":"ADBE Vector Group","hd":false},{"ty":"gr","it":[{"ind":0,"ty":"sh","ix":1,"ks":{"a":0,"k":{"i":[[0,0],[0,0],[0,0],[0,0]],"o":[[0,0],[0,0],[0,0],[0,0]],"v":[[-74.898,-5],[74.898,-5],[74.898,5],[-74.898,5]],"c":true},"ix":2},"nm":"Path 1","mn":"ADBE Vector Shape - Group","hd":false},{"ty":"fl","c":{"a":0,"k":[0.690196096897,0.690196096897,0.690196096897,1],"ix":4},"o":{"a":0,"k":60,"ix":5},"r":1,"bm":0,"nm":"Fill 2","mn":"ADBE Vector Graphic - Fill","hd":false},{"ty":"tr","p":{"a":0,"k":[131.102,27.798],"ix":2},"a":{"a":0,"k":[0,0],"ix":1},"s":{"a":0,"k":[100,100],"ix":3},"r":{"a":0,"k":0,"ix":6},"o":{"a":0,"k":100,"ix":7},"sk":{"a":0,"k":0,"ix":4},"sa":{"a":0,"k":0,"ix":5},"nm":"Transform"}],"nm":"Group 5","np":4,"cix":2,"bm":0,"ix":5,"mn":"ADBE Vector Group","hd":false},{"ty":"gr","it":[{"ind":0,"ty":"sh","ix":1,"ks":{"a":0,"k":{"i":[[0,0],[0,0],[0,0],[0,0]],"o":[[0,0],[0,0],[0,0],[0,0]],"v":[[-97,-5],[97,-5],[97,5],[-97,5]],"c":true},"ix":2},"nm":"Path 1","mn":"ADBE Vector Shape - Group","hd":false},{"ty":"fl","c":{"a":0,"k":[0.690196096897,0.690196096897,0.690196096897,1],"ix":4},"o":{"a":0,"k":60,"ix":5},"r":1,"bm":0,"nm":"Fill 2","mn":"ADBE Vector Graphic - Fill","hd":false},{"ty":"tr","p":{"a":0,"k":[109,73],"ix":2},"a":{"a":0,"k":[0,0],"ix":1},"s":{"a":0,"k":[100,100],"ix":3},"r":{"a":0,"k":0,"ix":6},"o":{"a":0,"k":100,"ix":7},"sk":{"a":0,"k":0,"ix":4},"sa":{"a":0,"k":0,"ix":5},"nm":"Transform"}],"nm":"Group 6","np":4,"cix":2,"bm":0,"ix":6,"mn":"ADBE Vector Group","hd":false},{"ty":"gr","it":[{"ind":0,"ty":"sh","ix":1,"ks":{"a":0,"k":{"i":[[0,0],[0,0],[0,0],[0,0]],"o":[[0,0],[0,0],[0,0],[0,0]],"v":[[-97,-5],[97,-5],[97,5],[-97,5]],"c":true},"ix":2},"nm":"Path 1","mn":"ADBE Vector Shape - Group","hd":false},{"ty":"fl","c":{"a":0,"k":[0.690196096897,0.690196096897,0.690196096897,1],"ix":4},"o":{"a":0,"k":60,"ix":5},"r":1,"bm":0,"nm":"Fill 2","mn":"ADBE Vector Graphic - Fill","hd":false},{"ty":"tr","p":{"a":0,"k":[109,56],"ix":2},"a":{"a":0,"k":[0,0],"ix":1},"s":{"a":0,"k":[100,100],"ix":3},"r":{"a":0,"k":0,"ix":6},"o":{"a":0,"k":100,"ix":7},"sk":{"a":0,"k":0,"ix":4},"sa":{"a":0,"k":0,"ix":5},"nm":"Transform"}],"nm":"Group 7","np":4,"cix":2,"bm":0,"ix":7,"mn":"ADBE Vector Group","hd":false}],"ip":0,"op":1800,"st":0,"bm":0},{"ddd":0,"ind":5,"ty":4,"nm":"Upcoming_Card 2 Outlines","sr":1,"ks":{"o":{"a":0,"k":100,"ix":11},"r":{"a":0,"k":0,"ix":10},"p":{"a":0,"k":[720,604,0],"ix":2},"a":{"a":0,"k":[109,45,0],"ix":1},"s":{"a":0,"k":[400,400,100],"ix":6}},"ao":0,"shapes":[{"ty":"gr","it":[{"ind":0,"ty":"sh","ix":1,"ks":{"a":0,"k":{"i":[[-0.063,-0.321],[0,0],[0,0],[-0.273,0],[0,0],[-0.23,-0.114],[0.408,-0.824],[0,0],[0.633,0],[0,0],[0.151,0.783],[0,0],[0,0.106],[0,0],[0,0],[0,0],[0.08,0.319],[0.001,0],[-0.321,0.081],[0,0],[0,0],[-0.042,0.009]],"o":[[0,0],[0,0],[0.227,-0.116],[0,0],[0.256,0],[0.824,0.408],[0,0],[-0.281,0.567],[0,0],[-0.798,0],[0,0],[-0.02,-0.104],[0,0],[0,0],[0,0],[-0.319,0.08],[0,-0.001],[-0.079,-0.322],[0,0],[0,0],[0.038,-0.017],[0.321,-0.063]],"v":[[-5.605,-7.823],[-5.605,-7.821],[-4.91,-4.213],[-4.152,-4.394],[7.766,-4.394],[8.505,-4.221],[9.258,-1.99],[6.557,3.465],[5.064,4.391],[-3.102,4.391],[-4.736,3.041],[-5.788,-2.414],[-5.818,-2.729],[-5.816,-2.638],[-6.648,-6.963],[-8.863,-6.405],[-9.587,-6.838],[-9.588,-6.84],[-9.15,-7.568],[-6.471,-8.242],[-6.421,-8.252],[-6.299,-8.29]],"c":true},"ix":2},"nm":"Path 1","mn":"ADBE Vector Shape - Group","hd":false},{"ind":1,"ty":"sh","ix":2,"ks":{"a":0,"k":{"i":[[-0.656,0],[0,-0.661],[0.656,0],[0,0.662]],"o":[[0.656,0],[0,0.662],[-0.656,0],[0,-0.661]],"v":[[3.96,5.957],[5.148,7.155],[3.96,8.353],[2.773,7.155]],"c":true},"ix":2},"nm":"Path 2","mn":"ADBE Vector Shape - Group","hd":false},{"ind":2,"ty":"sh","ix":3,"ks":{"a":0,"k":{"i":[[-0.656,0],[0,-0.661],[0.655,0],[0,0.662]],"o":[[0.655,0],[0,0.662],[-0.656,0],[0,-0.661]],"v":[[-2.37,5.957],[-1.184,7.155],[-2.37,8.353],[-3.557,7.155]],"c":true},"ix":2},"nm":"Path 3","mn":"ADBE Vector Shape - Group","hd":false},{"ty":"mm","mm":1,"nm":"Merge Paths 1","mn":"ADBE Vector Filter - Merge","hd":false},{"ty":"fl","c":{"a":0,"k":[1,1,1,1],"ix":4},"o":{"a":0,"k":100,"ix":5},"r":1,"bm":0,"nm":"Fill 1","mn":"ADBE Vector Graphic - Fill","hd":false},{"ty":"tr","p":{"a":0,"k":[28.219,28.37],"ix":2},"a":{"a":0,"k":[0,0],"ix":1},"s":{"a":0,"k":[100,100],"ix":3},"r":{"a":0,"k":0,"ix":6},"o":{"a":0,"k":100,"ix":7},"sk":{"a":0,"k":0,"ix":4},"sa":{"a":0,"k":0,"ix":5},"nm":"Transform"}],"nm":"Group 1","np":7,"cix":2,"bm":0,"ix":1,"mn":"ADBE Vector Group","hd":false},{"ty":"gr","it":[{"ind":0,"ty":"sh","ix":1,"ks":{"a":0,"k":{"i":[[-8.76,0],[0,-8.76],[8.76,0],[0,8.76]],"o":[[8.76,0],[0,8.76],[-8.76,0],[0,-8.76]],"v":[[0,-15.861],[15.861,0],[0,15.861],[-15.861,0]],"c":true},"ix":2},"nm":"Path 1","mn":"ADBE Vector Shape - Group","hd":false},{"ty":"fl","c":{"a":0,"k":[0,0.583999992819,1,1],"ix":4},"o":{"a":0,"k":100,"ix":5},"r":1,"bm":0,"nm":"Fill 1","mn":"ADBE Vector Graphic - Fill","hd":false},{"ty":"tr","p":{"a":0,"k":[28,28],"ix":2},"a":{"a":0,"k":[0,0],"ix":1},"s":{"a":0,"k":[100,100],"ix":3},"r":{"a":0,"k":0,"ix":6},"o":{"a":0,"k":100,"ix":7},"sk":{"a":0,"k":0,"ix":4},"sa":{"a":0,"k":0,"ix":5},"nm":"Transform"}],"nm":"Group 4","np":4,"cix":2,"bm":0,"ix":4,"mn":"ADBE Vector Group","hd":false},{"ty":"gr","it":[{"ind":0,"ty":"sh","ix":1,"ks":{"a":0,"k":{"i":[[0,0],[0,0],[0,0],[0,0]],"o":[[0,0],[0,0],[0,0],[0,0]],"v":[[-74.898,-5],[74.898,-5],[74.898,5],[-74.898,5]],"c":true},"ix":2},"nm":"Path 1","mn":"ADBE Vector Shape - Group","hd":false},{"ty":"fl","c":{"a":0,"k":[0.690196096897,0.690196096897,0.690196096897,1],"ix":4},"o":{"a":0,"k":60,"ix":5},"r":1,"bm":0,"nm":"Fill 2","mn":"ADBE Vector Graphic - Fill","hd":false},{"ty":"tr","p":{"a":0,"k":[131.102,27.798],"ix":2},"a":{"a":0,"k":[0,0],"ix":1},"s":{"a":0,"k":[100,100],"ix":3},"r":{"a":0,"k":0,"ix":6},"o":{"a":0,"k":100,"ix":7},"sk":{"a":0,"k":0,"ix":4},"sa":{"a":0,"k":0,"ix":5},"nm":"Transform"}],"nm":"Group 5","np":4,"cix":2,"bm":0,"ix":5,"mn":"ADBE Vector Group","hd":false},{"ty":"gr","it":[{"ind":0,"ty":"sh","ix":1,"ks":{"a":0,"k":{"i":[[0,0],[0,0],[0,0],[0,0]],"o":[[0,0],[0,0],[0,0],[0,0]],"v":[[-97,-5],[97,-5],[97,5],[-97,5]],"c":true},"ix":2},"nm":"Path 1","mn":"ADBE Vector Shape - Group","hd":false},{"ty":"fl","c":{"a":0,"k":[0.690196096897,0.690196096897,0.690196096897,1],"ix":4},"o":{"a":0,"k":60,"ix":5},"r":1,"bm":0,"nm":"Fill 2","mn":"ADBE Vector Graphic - Fill","hd":false},{"ty":"tr","p":{"a":0,"k":[109,73],"ix":2},"a":{"a":0,"k":[0,0],"ix":1},"s":{"a":0,"k":[100,100],"ix":3},"r":{"a":0,"k":0,"ix":6},"o":{"a":0,"k":100,"ix":7},"sk":{"a":0,"k":0,"ix":4},"sa":{"a":0,"k":0,"ix":5},"nm":"Transform"}],"nm":"Group 6","np":4,"cix":2,"bm":0,"ix":6,"mn":"ADBE Vector Group","hd":false},{"ty":"gr","it":[{"ind":0,"ty":"sh","ix":1,"ks":{"a":0,"k":{"i":[[0,0],[0,0],[0,0],[0,0]],"o":[[0,0],[0,0],[0,0],[0,0]],"v":[[-97,-5],[97,-5],[97,5],[-97,5]],"c":true},"ix":2},"nm":"Path 1","mn":"ADBE Vector Shape - Group","hd":false},{"ty":"fl","c":{"a":0,"k":[0.690196096897,0.690196096897,0.690196096897,1],"ix":4},"o":{"a":0,"k":60,"ix":5},"r":1,"bm":0,"nm":"Fill 2","mn":"ADBE Vector Graphic - Fill","hd":false},{"ty":"tr","p":{"a":0,"k":[109,56],"ix":2},"a":{"a":0,"k":[0,0],"ix":1},"s":{"a":0,"k":[100,100],"ix":3},"r":{"a":0,"k":0,"ix":6},"o":{"a":0,"k":100,"ix":7},"sk":{"a":0,"k":0,"ix":4},"sa":{"a":0,"k":0,"ix":5},"nm":"Transform"}],"nm":"Group 7","np":4,"cix":2,"bm":0,"ix":7,"mn":"ADBE Vector Group","hd":false}],"ip":0,"op":1800,"st":0,"bm":0},{"ddd":0,"ind":6,"ty":4,"nm":"Upcoming_Card 1 Outlines","sr":1,"ks":{"o":{"a":0,"k":100,"ix":11},"r":{"a":0,"k":0,"ix":10},"p":{"a":0,"k":[720,204,0],"ix":2},"a":{"a":0,"k":[109,45,0],"ix":1},"s":{"a":0,"k":[400,400,100],"ix":6}},"ao":0,"shapes":[{"ty":"gr","it":[{"ind":0,"ty":"sh","ix":1,"ks":{"a":0,"k":{"i":[[1.648,0],[1.671,-0.093],[0.086,-0.255],[0,0],[0,0],[0,-0.017],[-0.122,-0.025],[0,0],[0,0],[-0.017,0.003],[-0.001,0.125],[0,0],[0,0],[0.304,0.018]],"o":[[-1.659,0],[-0.276,0.015],[0,0],[0,0],[-0.003,0.016],[0,0.129],[0,0],[0,0],[0.018,0],[0.127,-0.025],[0,0],[0,0],[-0.059,-0.299],[-1.551,-0.092]],"v":[[0.165,-5.993],[-4.831,-5.854],[-5.426,-5.4],[-5.451,-5.313],[-6.128,-1.792],[-6.133,-1.742],[-5.919,-1.48],[-5.865,-1.473],[6.008,-1.473],[6.061,-1.479],[6.277,-1.74],[6.271,-1.792],[5.577,-5.318],[4.962,-5.855]],"c":true},"ix":2},"nm":"Path 1","mn":"ADBE Vector Shape - Group","hd":false},{"ind":1,"ty":"sh","ix":2,"ks":{"a":0,"k":{"i":[[0.742,0],[0,-0.759],[-0.743,0],[0,0.76]],"o":[[-0.743,0],[0,0.76],[0.742,0],[0,-0.759]],"v":[[5.667,0.197],[4.322,1.572],[5.667,2.947],[7.012,1.572]],"c":true},"ix":2},"nm":"Path 2","mn":"ADBE Vector Shape - Group","hd":false},{"ind":2,"ty":"sh","ix":3,"ks":{"a":0,"k":{"i":[[0.742,0],[0,-0.759],[-0.743,0],[0,0.76]],"o":[[-0.743,0],[0,0.76],[0.742,0],[0,-0.759]],"v":[[-5.667,0.197],[-7.012,1.572],[-5.667,2.947],[-4.322,1.572]],"c":true},"ix":2},"nm":"Path 3","mn":"ADBE Vector Shape - Group","hd":false},{"ind":3,"ty":"sh","ix":4,"ks":{"a":0,"k":{"i":[[-0.436,0],[-0.302,-0.015],[-0.105,-0.224],[0,0],[0,-0.038],[-1.202,-0.087],[-0.073,-0.277],[0,0],[0.006,-0.035],[0,-0.566],[0,0],[0.147,0],[0,0],[0,0],[0.369,0],[0,0],[0,0.369],[0,0],[0,0],[0,0],[0.369,0],[0,0],[0,0.369],[0,0],[0,0],[0,0.148],[0,0],[-0.47,0.245],[0,0.014],[-0.007,0.023],[0,0],[-0.282,0.021],[-1.174,0.031],[0,0],[-0.014,0.032],[0,0],[-0.257,0.012]],"o":[[0.416,0],[0.247,0.013],[0,0],[0.017,0.036],[1.177,0.031],[0.286,0.02],[0,0],[0.009,0.037],[0.469,0.245],[0,0],[0,0.148],[0,0],[0,0],[0,0.369],[0,0],[-0.369,0],[0,0],[0,0],[0,0],[0,0.369],[0,0],[-0.37,0],[0,0],[0,0],[-0.148,0],[0,0],[0,-0.567],[-0.003,-0.013],[0,-0.024],[0,0],[0.075,-0.272],[1.18,-0.087],[0,0.002],[0,-0.035],[0,0],[0.099,-0.238],[0.35,-0.018]],"v":[[0.057,-7.958],[1.132,-7.936],[1.704,-7.549],[1.977,-6.962],[2.001,-6.85],[5.572,-6.673],[6.171,-6.174],[7.563,-0.827],[7.568,-0.717],[8.357,0.587],[8.357,5.234],[8.089,5.501],[7.012,5.501],[7.012,7.29],[6.344,7.958],[5.663,7.958],[4.995,7.29],[4.995,5.501],[-4.995,5.501],[-4.995,7.29],[-5.663,7.958],[-6.342,7.958],[-7.012,7.29],[-7.012,5.501],[-8.089,5.501],[-8.357,5.234],[-8.357,0.587],[-7.566,-0.717],[-7.57,-0.758],[-7.56,-0.829],[-6.094,-6.184],[-5.499,-6.673],[-1.967,-6.852],[-1.967,-6.85],[-1.947,-6.954],[-1.708,-7.523],[-1.124,-7.932]],"c":true},"ix":2},"nm":"Path 4","mn":"ADBE Vector Shape - Group","hd":false},{"ty":"mm","mm":1,"nm":"Merge Paths 1","mn":"ADBE Vector Filter - Merge","hd":false},{"ty":"fl","c":{"a":0,"k":[0.980000035903,0.980000035903,0.980000035903,1],"ix":4},"o":{"a":0,"k":100,"ix":5},"r":1,"bm":0,"nm":"Fill 1","mn":"ADBE Vector Graphic - Fill","hd":false},{"ty":"tr","p":{"a":0,"k":[28.398,28],"ix":2},"a":{"a":0,"k":[0,0],"ix":1},"s":{"a":0,"k":[100,100],"ix":3},"r":{"a":0,"k":0,"ix":6},"o":{"a":0,"k":100,"ix":7},"sk":{"a":0,"k":0,"ix":4},"sa":{"a":0,"k":0,"ix":5},"nm":"Transform"}],"nm":"Group 1","np":8,"cix":2,"bm":0,"ix":1,"mn":"ADBE Vector Group","hd":false},{"ty":"gr","it":[{"ind":0,"ty":"sh","ix":1,"ks":{"a":0,"k":{"i":[[-8.791,0],[0,-8.791],[8.791,0],[0,8.79]],"o":[[8.791,0],[0,8.79],[-8.791,0],[0,-8.791]],"v":[[0,-15.917],[15.917,0.001],[0,15.917],[-15.917,0.001]],"c":true},"ix":2},"nm":"Path 1","mn":"ADBE Vector Shape - Group","hd":false},{"ty":"fl","c":{"a":0,"k":[0,0.583999992819,1,1],"ix":4},"o":{"a":0,"k":100,"ix":5},"r":1,"bm":0,"nm":"Fill 1","mn":"ADBE Vector Graphic - Fill","hd":false},{"ty":"tr","p":{"a":0,"k":[28,28],"ix":2},"a":{"a":0,"k":[0,0],"ix":1},"s":{"a":0,"k":[100,100],"ix":3},"r":{"a":0,"k":0,"ix":6},"o":{"a":0,"k":100,"ix":7},"sk":{"a":0,"k":0,"ix":4},"sa":{"a":0,"k":0,"ix":5},"nm":"Transform"}],"nm":"Group 4","np":4,"cix":2,"bm":0,"ix":4,"mn":"ADBE Vector Group","hd":false},{"ty":"gr","it":[{"ind":0,"ty":"sh","ix":1,"ks":{"a":0,"k":{"i":[[0,0],[0,0],[0,0],[0,0]],"o":[[0,0],[0,0],[0,0],[0,0]],"v":[[-74.898,-5],[74.898,-5],[74.898,5],[-74.898,5]],"c":true},"ix":2},"nm":"Path 1","mn":"ADBE Vector Shape - Group","hd":false},{"ty":"fl","c":{"a":0,"k":[0.690196096897,0.690196096897,0.690196096897,1],"ix":4},"o":{"a":0,"k":60,"ix":5},"r":1,"bm":0,"nm":"Fill 1","mn":"ADBE Vector Graphic - Fill","hd":false},{"ty":"tr","p":{"a":0,"k":[131.102,27.798],"ix":2},"a":{"a":0,"k":[0,0],"ix":1},"s":{"a":0,"k":[100,100],"ix":3},"r":{"a":0,"k":0,"ix":6},"o":{"a":0,"k":100,"ix":7},"sk":{"a":0,"k":0,"ix":4},"sa":{"a":0,"k":0,"ix":5},"nm":"Transform"}],"nm":"Group 5","np":4,"cix":2,"bm":0,"ix":5,"mn":"ADBE Vector Group","hd":false},{"ty":"gr","it":[{"ind":0,"ty":"sh","ix":1,"ks":{"a":0,"k":{"i":[[0,0],[0,0],[0,0],[0,0]],"o":[[0,0],[0,0],[0,0],[0,0]],"v":[[-97,-5],[97,-5],[97,5],[-97,5]],"c":true},"ix":2},"nm":"Path 1","mn":"ADBE Vector Shape - Group","hd":false},{"ty":"fl","c":{"a":0,"k":[0.690196096897,0.690196096897,0.690196096897,1],"ix":4},"o":{"a":0,"k":60,"ix":5},"r":1,"bm":0,"nm":"Fill 1","mn":"ADBE Vector Graphic - Fill","hd":false},{"ty":"tr","p":{"a":0,"k":[109,73],"ix":2},"a":{"a":0,"k":[0,0],"ix":1},"s":{"a":0,"k":[100,100],"ix":3},"r":{"a":0,"k":0,"ix":6},"o":{"a":0,"k":100,"ix":7},"sk":{"a":0,"k":0,"ix":4},"sa":{"a":0,"k":0,"ix":5},"nm":"Transform"}],"nm":"Group 6","np":4,"cix":2,"bm":0,"ix":6,"mn":"ADBE Vector Group","hd":false},{"ty":"gr","it":[{"ind":0,"ty":"sh","ix":1,"ks":{"a":0,"k":{"i":[[0,0],[0,0],[0,0],[0,0]],"o":[[0,0],[0,0],[0,0],[0,0]],"v":[[-97,-5],[97,-5],[97,5],[-97,5]],"c":true},"ix":2},"nm":"Path 1","mn":"ADBE Vector Shape - Group","hd":false},{"ty":"fl","c":{"a":0,"k":[0.690196096897,0.690196096897,0.690196096897,1],"ix":4},"o":{"a":0,"k":60,"ix":5},"r":1,"bm":0,"nm":"Fill 1","mn":"ADBE Vector Graphic - Fill","hd":false},{"ty":"tr","p":{"a":0,"k":[109,56],"ix":2},"a":{"a":0,"k":[0,0],"ix":1},"s":{"a":0,"k":[100,100],"ix":3},"r":{"a":0,"k":0,"ix":6},"o":{"a":0,"k":100,"ix":7},"sk":{"a":0,"k":0,"ix":4},"sa":{"a":0,"k":0,"ix":5},"nm":"Transform"}],"nm":"Group 7","np":4,"cix":2,"bm":0,"ix":7,"mn":"ADBE Vector Group","hd":false}],"ip":0,"op":1800,"st":0,"bm":0}]}],"layers":[{"ddd":0,"ind":3,"ty":3,"nm":"Null 3","sr":1,"ks":{"o":{"a":0,"k":0,"ix":11},"r":{"a":0,"k":0,"ix":10},"p":{"a":0,"k":[624,-186,0],"ix":2},"a":{"a":0,"k":[0,0,0],"ix":1},"s":{"a":0,"k":[100,100,100],"ix":6}},"ao":0,"ip":0,"op":1800,"st":0,"bm":0},{"ddd":0,"ind":5,"ty":3,"nm":"Null 2 loop_Ani","parent":3,"sr":1,"ks":{"o":{"a":0,"k":0,"ix":11},"r":{"a":0,"k":0,"ix":10},"p":{"s":true,"x":{"a":0,"k":0,"ix":3},"y":{"a":1,"k":[{"i":{"x":[0.3],"y":[1]},"o":{"x":[0.17],"y":[0.075]},"t":297,"s":[80]},{"i":{"x":[0.9],"y":[1]},"o":{"x":[0.1],"y":[0]},"t":330,"s":[-120]},{"i":{"x":[0.4],"y":[1]},"o":{"x":[0.17],"y":[0.17]},"t":390,"s":[-120]},{"i":{"x":[0.9],"y":[1]},"o":{"x":[0.1],"y":[0]},"t":430,"s":[-520]},{"i":{"x":[0.4],"y":[1]},"o":{"x":[0.17],"y":[0.17]},"t":490,"s":[-520]},{"i":{"x":[0.9],"y":[1]},"o":{"x":[0.1],"y":[0]},"t":530,"s":[-920]},{"i":{"x":[0.4],"y":[1]},"o":{"x":[0.17],"y":[0.17]},"t":590,"s":[-920]},{"t":630,"s":[-1320]}],"ix":4}},"a":{"a":0,"k":[0,0,0],"ix":1},"s":{"a":0,"k":[100,100,100],"ix":6}},"ao":0,"ip":297,"op":1800,"st":0,"bm":0},{"ddd":0,"ind":6,"ty":3,"nm":"Null 2 ref","sr":1,"ks":{"o":{"a":0,"k":0,"ix":11},"r":{"a":0,"k":0,"ix":10},"p":{"s":true,"x":{"a":1,"k":[{"i":{"x":[0.3],"y":[1]},"o":{"x":[0.17],"y":[0]},"t":297,"s":[624]},{"i":{"x":[0.9],"y":[1]},"o":{"x":[0.1],"y":[0]},"t":330,"s":[624]},{"i":{"x":[0.4],"y":[1]},"o":{"x":[0.17],"y":[0]},"t":390,"s":[624]},{"i":{"x":[0.9],"y":[1]},"o":{"x":[0.1],"y":[0]},"t":430,"s":[624]},{"i":{"x":[0.4],"y":[1]},"o":{"x":[0.17],"y":[0]},"t":490,"s":[624]},{"i":{"x":[0.9],"y":[1]},"o":{"x":[0.1],"y":[0]},"t":530,"s":[624]},{"i":{"x":[0.4],"y":[1]},"o":{"x":[0.17],"y":[0]},"t":590,"s":[624]},{"i":{"x":[0.9],"y":[1]},"o":{"x":[0.1],"y":[0]},"t":630,"s":[624]},{"i":{"x":[0.4],"y":[1]},"o":{"x":[0.17],"y":[0]},"t":696,"s":[624]},{"t":716,"s":[624]}],"ix":3},"y":{"a":1,"k":[{"i":{"x":[0.3],"y":[1]},"o":{"x":[0.17],"y":[0.037]},"t":297,"s":[176]},{"i":{"x":[0.9],"y":[1]},"o":{"x":[0.1],"y":[0]},"t":330,"s":[-224]},{"i":{"x":[0.4],"y":[1]},"o":{"x":[0.17],"y":[0.17]},"t":390,"s":[-224]},{"i":{"x":[0.9],"y":[1]},"o":{"x":[0.1],"y":[0]},"t":430,"s":[-624]},{"i":{"x":[0.4],"y":[1]},"o":{"x":[0.17],"y":[0.17]},"t":490,"s":[-624]},{"i":{"x":[0.9],"y":[1]},"o":{"x":[0.1],"y":[0]},"t":530,"s":[-1024]},{"i":{"x":[0.4],"y":[1]},"o":{"x":[0.17],"y":[0.17]},"t":590,"s":[-1024]},{"i":{"x":[0.9],"y":[1]},"o":{"x":[0.1],"y":[0]},"t":630,"s":[-1424]},{"i":{"x":[0.4],"y":[1]},"o":{"x":[0.17],"y":[0.17]},"t":696,"s":[-1421]},{"i":{"x":[0.9],"y":[1]},"o":{"x":[0.167],"y":[0]},"t":716,"s":[-1813]},{"i":{"x":[0.3],"y":[1]},"o":{"x":[0.17],"y":[0.17]},"t":756,"s":[-1813]},{"t":776,"s":[-2133]}],"ix":4}},"a":{"a":0,"k":[0,0,0],"ix":1},"s":{"a":0,"k":[100,100,100],"ix":6}},"ao":0,"ip":297,"op":1800,"st":0,"bm":0},{"ddd":0,"ind":8,"ty":1,"nm":"Mask 2","parent":3,"td":1,"sr":1,"ks":{"o":{"a":0,"k":100,"ix":11},"r":{"a":0,"k":0,"ix":10},"p":{"a":0,"k":[0,0,0],"ix":2},"a":{"a":0,"k":[720,1520,0],"ix":1},"s":{"a":0,"k":[100,100,100],"ix":6}},"ao":0,"hasMask":true,"masksProperties":[{"inv":false,"mode":"a","pt":{"a":0,"k":{"i":[[0,0],[0,0],[0,0],[0,0]],"o":[[0,0],[0,0],[0,0],[0,0]],"v":[[1572,1728],[-32,1728],[-32,2480],[1572,2480]],"c":true},"ix":1},"o":{"a":0,"k":100,"ix":3},"x":{"a":0,"k":0,"ix":4},"nm":"Mask 1"}],"sw":1440,"sh":3040,"sc":"#2f2f2f","ip":0,"op":1800,"st":0,"bm":0},{"ddd":0,"ind":9,"ty":0,"nm":"Offer Cards Precomp ","parent":5,"tt":1,"refId":"comp_0","sr":1,"ks":{"o":{"a":0,"k":100,"ix":11},"r":{"a":0,"k":0,"ix":10},"p":{"s":true,"x":{"a":0,"k":0,"ix":3},"y":{"a":1,"k":[{"i":{"x":[0.83],"y":[0.887]},"o":{"x":[0.6],"y":[0]},"t":700,"s":[1698]},{"t":722,"s":[1638]}],"ix":4}},"a":{"a":0,"k":[720,1800,0],"ix":1},"s":{"a":0,"k":[100,100,100],"ix":6}},"ao":0,"w":1440,"h":3600,"ip":297,"op":1800,"st":0,"bm":0}],"markers":[]}